pi_pir_webthing/__init__.py
pi_pir_webthing/app.py
pi_pir_webthing/motionsensor_webthing.py
pi_pir_webthing-0.1.1.dist-info/LICENSE
pi_pir_webthing-0.1.1.dist-info/METADATA
pi_pir_webthing-0.1.1.dist-info/WHEEL
pi_pir_webthing-0.1.1.dist-info/entry_points.txt
pi_pir_webthing-0.1.1.dist-info/top_level.txt
pi_pir_webthing-0.1.1.dist-info/RECORD
