Metadata-Version: 2.1
Name: pi-pir-webthing
Version: 0.1.1
Summary: A web connected PIR motion sensor detecting movement running on Raspberry Pi
Home-page: https://github.com/grro/pi_pir_webthing
Author: Gregor Roth
Author-email: gregor.roth@web.de
License: MIT
Keywords: webthings,home automation,PIR,motion,sensor,movement
Platform: UNKNOWN
Classifier: Programming Language :: Python :: 3
Classifier: License :: OSI Approved :: Apache Software License
Classifier: Operating System :: OS Independent
Classifier: Development Status :: 3 - Alpha
Requires-Dist: webthing (==0.15.0)
Requires-Dist: RPi.GPIO
